skyant/ui/__init__.py
skyant/ui/app/__init__.py
skyant/ui/app/_dash.py
skyant_ui-0.0.1.post1.dist-info/LICENSE
skyant_ui-0.0.1.post1.dist-info/METADATA
skyant_ui-0.0.1.post1.dist-info/WHEEL
skyant_ui-0.0.1.post1.dist-info/top_level.txt
skyant_ui-0.0.1.post1.dist-info/RECORD
