Metadata-Version: 2.1
Name: skyant-ui
Version: 0.0.1.post1
Summary: Preconfigured Plotly Dash & some tools
Home-page: https://skyant.dev
Author: Iurii Tarasenko
Author-email: info@skyant.dev
License: MIT
Project-URL: Source & issues, https://gitlab.com/skyant/python/ui
Project-URL: Documentation, https://docs.skyant.dev/projects/ui
Keywords: visualization,data,web,dash,react
Classifier: Programming Language :: Python :: 3.10
Classifier: Intended Audience :: Developers
Classifier: Intended Audience :: Information Technology
Classifier: Topic :: Software Development :: Libraries :: Python Modules
Requires-Python: >=3.10
License-File: LICENSE
Requires-Dist: dash[compress] (>=2.5)
Requires-Dist: dash-bootstrap-components
Requires-Dist: python-jose
Requires-Dist: asgiref
Requires-Dist: hypercorn
Requires-Dist: jupyter-dash
Requires-Dist: python-dotenv
